hscraper/__init__.py
hscraper/h_core.py
hscraper/scraper.py
hscraper/web_retriever.py
hscraper-0.51.data/data/LICENSE
hscraper-0.51.dist-info/METADATA
hscraper-0.51.dist-info/RECORD
hscraper-0.51.dist-info/WHEEL
hscraper-0.51.dist-info/entry_points.txt
hscraper-0.51.dist-info/top_level.txt
